{
  "id": "enterprise/schema-registry",
  "title": "Schema Registry",
  "description": "Backup and restore Confluent Schema Registry with OSO Kafka Backup Enterprise",
  "source": "@site/docs/enterprise/schema-registry.md",
  "sourceDirName": "enterprise",
  "slug": "/enterprise/schema-registry",
  "permalink": "/enterprise/schema-registry",
  "draft": false,
  "unlisted": false,
  "editUrl": "https://github.com/osodevops/kafka-backup-docs/tree/main/docs/docs/enterprise/schema-registry.md",
  "tags": [],
  "version": "current",
  "sidebarPosition": 5,
  "frontMatter": {
    "title": "Schema Registry",
    "description": "Backup and restore Confluent Schema Registry with OSO Kafka Backup Enterprise",
    "sidebar_position": 5
  },
  "sidebar": "docsSidebar",
  "previous": {
    "title": "Audit Logging",
    "permalink": "/enterprise/audit-logging"
  },
  "next": {
    "title": "Licensing",
    "permalink": "/enterprise/licensing"
  }
}