{
  "id": "operator/crds/kafkabackup",
  "title": "KafkaBackup",
  "description": "KafkaBackup Custom Resource Definition reference",
  "source": "@site/docs/operator/crds/kafkabackup.md",
  "sourceDirName": "operator/crds",
  "slug": "/operator/crds/kafkabackup",
  "permalink": "/operator/crds/kafkabackup",
  "draft": false,
  "unlisted": false,
  "editUrl": "https://github.com/osodevops/kafka-backup-docs/tree/main/docs/docs/operator/crds/kafkabackup.md",
  "tags": [],
  "version": "current",
  "sidebarPosition": 1,
  "frontMatter": {
    "title": "KafkaBackup",
    "description": "KafkaBackup Custom Resource Definition reference",
    "sidebar_position": 1
  },
  "sidebar": "docsSidebar",
  "previous": {
    "title": "Configuration",
    "permalink": "/operator/configuration"
  },
  "next": {
    "title": "KafkaRestore",
    "permalink": "/operator/crds/kafkarestore"
  }
}